chat/__init__.py
chat/__main__.py
chat/chat.py
chat_True_Owl-0.0.1.dist-info/METADATA
chat_True_Owl-0.0.1.dist-info/WHEEL
chat_True_Owl-0.0.1.dist-info/top_level.txt
chat_True_Owl-0.0.1.dist-info/RECORD
