Metadata-Version: 2.1
Name: chat-True-Owl
Version: 0.0.1
Summary: Education material "simple chat program"
Author: eunwoo
Author-email: eunwoo8383@icloud.com
Classifier: Programming Language :: Python :: 3
Classifier: License :: OSI Approved :: MIT License
Classifier: Operating System :: OS Independent
